geneplore_api/__init__.py
geneplore_api/api_sync.py
geneplore_api-3.1.1.dist-info/LICENSE
geneplore_api-3.1.1.dist-info/METADATA
geneplore_api-3.1.1.dist-info/WHEEL
geneplore_api-3.1.1.dist-info/top_level.txt
geneplore_api-3.1.1.dist-info/RECORD
