Metadata-Version: 2.1
Name: geneplore_api
Version: 3.1.1
Summary: A Python client for the Geneplore API.
Author-email: thegamebegins25 <will@geneplore.com>
Project-URL: Homepage, https://github.com/GeneploreAI/geneplore-libraries
Project-URL: Bug Tracker, https://github.com/GeneploreAI/geneplore-libraries/issues
Classifier: Programming Language :: Python :: 3
Classifier: License :: OSI Approved :: MIT License
Classifier: Operating System :: OS Independent
Classifier: Development Status :: 3 - Alpha
Requires-Python: >=3.7
License-File: LICENSE
Requires-Dist: requests
